pyrecli/__init__.py
pyrecli/command/cctoken.py
pyrecli/command/docs.py
pyrecli/command/grabinv.py
pyrecli/command/rename.py
pyrecli/command/scan.py
pyrecli/command/script.py
pyrecli/command/send.py
pyrecli/command/slice.py
pyrecli/pyrecli.py
pyrecli/util.py
pyrecli-0.3.7.dist-info/METADATA
pyrecli-0.3.7.dist-info/WHEEL
pyrecli-0.3.7.dist-info/entry_points.txt
pyrecli-0.3.7.dist-info/licenses/LICENSE
pyrecli-0.3.7.dist-info/RECORD
