Metadata-Version: 2.4
Name: pyrecli
Version: 0.3.7
Summary: Command line utilities for DiamondFire templates
License-Expression: MIT
License-File: LICENSE
Keywords: diamondfire,minecraft,template,cli,tools
Author: Amp
Requires-Python: >=3.10
Classifier: Programming Language :: Python :: 3
Classifier: Programming Language :: Python :: 3.10
Classifier: Programming Language :: Python :: 3.11
Classifier: Programming Language :: Python :: 3.12
Classifier: Programming Language :: Python :: 3.13
Classifier: Programming Language :: Python :: 3.14
Provides-Extra: dev
Requires-Dist: dfpyre (>=0.11.0)
Requires-Dist: pytest (>=9.0.2) ; extra == "dev"
Requires-Dist: rapidnbt (>=1.3.5)
Requires-Dist: twine (>=6.2.0) ; extra == "dev"
Project-URL: Repository, https://github.com/Amp63/pyrecli
